<TableList affairType="HTFKSQB_FGCL" modes="export,push" is_push="true">
    <Table id="-5832565156998068636" name="formmain_0229" display="formmain_0229" tabletype="master" onwertable="" onwerfield="">
        <FieldList>
            <Field id="7007767428426253360" name="id" display="id" fieldtype="long" fieldlength="20" is_null="true" is_primary="true" classname="" barcode=""/>
            <Field id="5605984638073064736" name="state" display="审核状态" fieldtype="int" fieldlength="10" is_null="true" is_primary="false" classname="" barcode=""/>
            <Field id="8755261256306738350" name="start_member_id" display="发起人" fieldtype="long" fieldlength="20" is_null="true" is_primary="false" classname="" barcode=""/>
            <Field id="3204476196829285190" name="start_date" display="发起时间" fieldtype="DATETIME" fieldlength="" is_null="true" is_primary="false" classname="" barcode=""/>
            <Field id="5321486387161221155" name="approve_member_id" display="审核人" fieldtype="long" fieldlength="20" is_null="true" is_primary="false" classname="" barcode=""/>
            <Field id="-2490448490810685316" name="approve_date" display="审核时间" fieldtype="DATETIME" fieldlength="" is_null="true" is_primary="false" classname="" barcode=""/>
            <Field id="-3716938243050879647" name="finishedflag" display="流程状态" fieldtype="int" fieldlength="10" is_null="true" is_primary="false" classname="" barcode=""/>
            <Field id="-6609181944571803467" name="ratifyflag" display="核定状态" fieldtype="int" fieldlength="10" is_null="true" is_primary="false" classname="" barcode=""/>
            <Field id="-2792128723300237253" name="ratify_member_id" display="核定人" fieldtype="long" fieldlength="20" is_null="true" is_primary="false" classname="" barcode=""/>
            <Field id="-657079682823929390" name="ratify_date" display="核定时间" fieldtype="DATETIME" fieldlength="" is_null="true" is_primary="false" classname="" barcode=""/>


            <Field id="9181195813892738919" name="field0001" display="申请人" fieldtype="VARCHAR" fieldlength="255,0" is_null="false" is_primary="false" classname="" barcode=""/>
            <Field id="1625031039623450022" name="field0002" display="申请部门" fieldtype="VARCHAR" fieldlength="255,0" is_null="false" is_primary="false" classname="" barcode=""/>
            <Field id="8785825349397334659" name="field0003" display="申请日期" fieldtype="TIMESTAMP" fieldlength="255,0" is_null="false" is_primary="false" classname="" barcode=""/>
            <Field id="7960411367237239523" name="field0004" display="公司名称" fieldtype="VARCHAR" fieldlength="255,0" is_null="false" is_primary="false" classname="ws_wrapper_local_company" barcode="company"/>
            <Field id="-8676823091469464017" name="field0005" display="收款单位名称" fieldtype="LONGTEXT" fieldlength="255,0" is_null="false" is_primary="false" classname="" barcode=""/>
            <Field id="-917550570132189945" name="field0006" display="收款单位开户行名称" fieldtype="VARCHAR" fieldlength="255,0" is_null="false" is_primary="false" classname="" barcode=""/>
            <Field id="1695461778313134970" name="field0007" display="本合同项下第几期付款" fieldtype="VARCHAR" fieldlength="255,0" is_null="false" is_primary="false" classname="" barcode=""/>
            <Field id="-2977211497198892440" name="field0008" display="是否在资金计划内" fieldtype="VARCHAR" fieldlength="255,0" is_null="false" is_primary="false" classname="" barcode=""/>
            <Field id="-7242412032316784454" name="field0009" display="收款单位开户行帐号" fieldtype="VARCHAR" fieldlength="255,0" is_null="false" is_primary="false" classname="" barcode=""/>
            <Field id="480847271119439490" name="field0010" display="联系人以及联系方式" fieldtype="LONGTEXT" fieldlength="255,0" is_null="false" is_primary="false" classname="" barcode=""/>
            <Field id="7669924736746801820" name="field0011" display="合同公文编号" fieldtype="VARCHAR" fieldlength="255,0" is_null="false" is_primary="false" classname="" barcode=""/>
            <Field id="5384047335941031857" name="field0012" display="本次付款金额小写" fieldtype="DECIMAL" fieldlength="20,3" is_null="false" is_primary="false" classname="ws" barcode="amount"/>
            <Field id="7932514888008352357" name="field0013" display="本次付款金额大写" fieldtype="VARCHAR" fieldlength="255,0" is_null="false" is_primary="false" classname="" barcode=""/>
            <Field id="-7265278037301901131" name="field0014" display="合同总金额" fieldtype="DECIMAL" fieldlength="22,2" is_null="false" is_primary="false" classname="" barcode=""/>
            <Field id="1754735639641866384" name="field0015" display="累计付款金额" fieldtype="DECIMAL" fieldlength="22,2" is_null="false" is_primary="false" classname="" barcode=""/>
            <Field id="6781826505186166004" name="field0016" display="累计支付比例" fieldtype="VARCHAR" fieldlength="255,0" is_null="false" is_primary="false" classname="" barcode=""/>
            <Field id="4292802112902481499" name="field0017" display="结算金额" fieldtype="DECIMAL" fieldlength="22,2" is_null="false" is_primary="false" classname="" barcode=""/>
            <Field id="1377250547169381099" name="field0018" display="目标成本" fieldtype="VARCHAR" fieldlength="255,0" is_null="false" is_primary="false" classname="" barcode=""/>
            <Field id="1399850554042240762" name="field0019" display="经办人" fieldtype="VARCHAR" fieldlength="255,0" is_null="false" is_primary="false" classname="" barcode=""/>
            <Field id="8349612801642352438" name="field0020" display="付款事由说明" fieldtype="VARCHAR" fieldlength="2550,0" is_null="false" is_primary="false" classname="" barcode=""/>
            <Field id="-981626127026667334" name="field0021" display="会计审核" fieldtype="VARCHAR" fieldlength="255,0" is_null="false" is_primary="false" classname="" barcode=""/>
            <Field id="275765431342223357" name="field0022" display="出纳付款" fieldtype="VARCHAR" fieldlength="255,0" is_null="false" is_primary="false" classname="" barcode=""/>
            <Field id="-8440584356155077568" name="field0023" display="附件" fieldtype="VARCHAR" fieldlength="255,0" is_null="false" is_primary="false" classname="" barcode=""/>
            <Field id="-5307067629443071313" name="field0024" display="本次付款金额小" fieldtype="DECIMAL" fieldlength="20,2" is_null="false" is_primary="false" classname="" barcode=""/>
            <Field id="-7878832832956578795" name="field0025" display="是否财务资金金融类" fieldtype="VARCHAR" fieldlength="255,0" is_null="false" is_primary="false" classname="" barcode=""/>
            <Field id="5303332375778905014" name="field0026" display="是否财务金融类" fieldtype="VARCHAR" fieldlength="255,0" is_null="false" is_primary="false" classname="" barcode=""/>
            <Field id="-7244159229446697816" name="field0027" display="合同服务内容" fieldtype="VARCHAR" fieldlength="2550,0" is_null="false" is_primary="false" classname="" barcode=""/>
            <Field id="-7894498614845815638" name="field0028" display="合同名称" fieldtype="VARCHAR" fieldlength="255,0" is_null="false" is_primary="false" classname="ws" barcode="payeeName"/>
            <Field id="6791899707599048376" name="field0029" display="是否人事行政类" fieldtype="VARCHAR" fieldlength="255,0" is_null="false" is_primary="false" classname="" barcode=""/>
            <Field id="3640994858639770733" name="field0030" display="几期项目" fieldtype="VARCHAR" fieldlength="255,0" is_null="false" is_primary="false" classname="" barcode=""/>
            <Field id="7892205773983989907" name="field0031" display="合计" fieldtype="DECIMAL" fieldlength="20,2" is_null="false" is_primary="false" classname="" barcode=""/>
            <Field id="8887586578177146950" name="field0037" display="部门文本" fieldtype="VARCHAR" fieldlength="255,0" is_null="false" is_primary="false" classname="" barcode=""/>
            <Field id="-8471206158044082403" name="field0038" display="单位" fieldtype="VARCHAR" fieldlength="255,0" is_null="false" is_primary="false" classname="" barcode=""/>
            <Field id="9106795353523506648" name="field0039" display="年" fieldtype="VARCHAR" fieldlength="255,0" is_null="false" is_primary="false" classname="" barcode=""/>
            <Field id="-7688547300296277955" name="field0042" display="月" fieldtype="VARCHAR" fieldlength="255,0" is_null="false" is_primary="false" classname="" barcode=""/>
            <Field id="7907214500064609355" name="field0043" display="日期时间" fieldtype="DATETIME" fieldlength="255,0" is_null="false" is_primary="false" classname="" barcode=""/>
            <Field id="-6955601568060192458" name="field0044" display="是否计提" fieldtype="VARCHAR" fieldlength="255,0" is_null="false" is_primary="false" classname="" barcode=""/>
            <Field id="-7274468781152583249" name="field0045" display="银行账户" fieldtype="VARCHAR" fieldlength="255,0" is_null="false" is_primary="false" classname="" barcode=""/>
            <Field id="8556750551769632156" name="field0046" display="摘要" fieldtype="VARCHAR" fieldlength="255,0" is_null="false" is_primary="false" classname="ws" barcode="remark"/>
            <Field id="3710378538190980852" name="field0047" display="借方科目" fieldtype="VARCHAR" fieldlength="255,0" is_null="false" is_primary="false" classname="" barcode=""/>
            <Field id="-7463882862201581687" name="field0048" display="贷方科目" fieldtype="VARCHAR" fieldlength="255,0" is_null="false" is_primary="false" classname="" barcode=""/>
            <Field id="7514583413704048705" name="field0049" display="贷方金额" fieldtype="DECIMAL" fieldlength="20,2" is_null="false" is_primary="false" classname="" barcode=""/>
            <Field id="3624866152739522515" name="field0050" display="收款单位名称1" fieldtype="VARCHAR" fieldlength="255,0" is_null="false" is_primary="false" classname="" barcode=""/>



            <Field id="-1752414975628655111" name="field0051" display="收款单位编号" fieldtype="VARCHAR" fieldlength="255,0" is_null="false" is_primary="false" classname="ws" barcode="outBgItemNumber"  />
            <Field id="-7277089329241370741" name="field0053" display="借方科目编码" fieldtype="DECIMAL" fieldlength="20,0" is_null="false" is_primary="false" classname="ws_wrapper" barcode="oppAccount" />
            <Field id="-3225778662370817963" name="field0056" display="贷方科目编码" fieldtype="DECIMAL" fieldlength="20,0" is_null="false" is_primary="false" classname="ws_wrapper" barcode="payerAccount" />
            <Field id="-4305770432658781100" name="field0055" display="银行账户编码" fieldtype="VARCHAR" fieldlength="255,0" is_null="false" is_primary="false" classname="ws_wrapper" barcode="payerAccountBank" />
        </FieldList>
        <IndexList>
        </IndexList>
    </Table>
    <Table id="0" name="formson_4980" display="组2" tabletype="slave" onwertable="formmain_0229" onwerfield="formmain_id">
        <FieldList>
            <Field id="-3289711795459960988" name="field0032" display="序号" fieldtype="DECIMAL" fieldlength="20,0" is_null="false" is_primary="false" classname="" barcode=""/>
            <Field id="-4247251150646919092" name="field0033" display="科目一" fieldtype="VARCHAR" fieldlength="255,0" is_null="false" is_primary="false" classname="" barcode=""/>
            <Field id="2235315507880611528" name="field0034" display="科目二" fieldtype="VARCHAR" fieldlength="255,0" is_null="false" is_primary="false" classname="" barcode=""/>
            <Field id="-2776666724249481230" name="field0035" display="科目三" fieldtype="VARCHAR" fieldlength="255,0" is_null="false" is_primary="false" classname="" barcode=""/>
            <Field id="222610349487573407" name="field0036" display="金额" fieldtype="DECIMAL" fieldlength="20,2" is_null="false" is_primary="false" classname="" barcode=""/>
            <Field id="5678015244627953981" name="field0040" display="预算剩余金额" fieldtype="DECIMAL" fieldlength="20,0" is_null="false" is_primary="false" classname="" barcode=""/>
            <Field id="4653732460239799665" name="field0041" display="是否超预算" fieldtype="VARCHAR" fieldlength="255,0" is_null="false" is_primary="false" classname="" barcode=""/>
        </FieldList>
        <IndexList>
        </IndexList>
    </Table>
</TableList>
